dl_translate/__init__.py
dl_translate/_pairs.py
dl_translate/_translation_model.py
dl_translate/utils.py
dl_translate/lang/__init__.py
dl_translate/lang/m2m100.py
dl_translate/lang/mbart50.py
dl_translate/lang/nllb200.py
dl_translate-0.3.1.dist-info/LICENSE
dl_translate-0.3.1.dist-info/METADATA
dl_translate-0.3.1.dist-info/WHEEL
dl_translate-0.3.1.dist-info/top_level.txt
dl_translate-0.3.1.dist-info/RECORD
