Metadata-Version: 2.1
Name: dl-translate
Version: 0.3.1
Summary: A deep learning-based translation library built on Huggingface transformers
Home-page: https://github.com/xhlulu/dl-translate
Author: Xing Han Lu
Author-email: github@xinghanlu.com
License: UNKNOWN
Platform: UNKNOWN
Classifier: Programming Language :: Python :: 3
Classifier: License :: OSI Approved :: MIT License
Classifier: Operating System :: OS Independent
Requires-Python: >=3.7
Provides-Extra: dev
